{"type": "Feature", "id": 12523334, "geometry": {"type": "Point", "coordinates": [168.294006, -16.3333]}, "properties": {"woe:id": 12523334, "woe:parent_id": 1050905, "woe:name": "Ulei Airport", "woe:placetype": 14, "woe:placetype_name": "Airport", "woe:lang": "ENG", "iso:country": "VU", "meta:provider": ["geoplanet:7.3.1", "geoplanet:7.3.2", "geoplanet:7.4.0", "geoplanet:7.4.1", "geoplanet:7.5.1", "geoplanet:7.5.2", "geoplanet:7.6.0", "geoplanet:7.8.1", "geoplanet:7.9.0", "geoplanet:7.10.0", "geoplanet:8.0.0", "woeplanet:8.0.0"], "meta:indexed": "2020-08-20T20:52:01.686292", "woe:alias_ENG_V": ["ULB Airport", "ULB"], "meta:updated": "2020-10-14T11:25:29.909620", "woe:hierarchy": {"continent": 24865674, "country": 23424907, "town": 0, "planet": 1, "county": 0, "suburb": 0, "state": 20069886, "region": 0, "localadmin": 0}, "woe:timezone_id": 28350940, "woe:hash": "rtpejdegws4n", "woe:centroid": [168.294006, -16.3333], "geom:latitude": -16.3333, "geom:longitude": 168.294006, "geom:hash": "rtpejdegws4n", "woe:latitude": -16.3333, "geom:centroid": [168.294006, -16.3333], "woe:longitude": 168.294006, "woe:repo": "woeplanet-airport-vu", "geom:area": 0.0, "woe:scale": 19}}